{
  "kind": "collectionType",
  "collectionName": "home_pages",
  "info": {
    "singularName": "home-page",
    "pluralName": "home-pages",
    "displayName": "HomePage",
    "description": ""
  },
  "options": {
    "draftAndPublish": true
  },
  "pluginOptions": {
    "webtools": {
      "enabled": true
    }
  },
  "attributes": {
    "url_alias": {
      "type": "relation",
      "relation": "oneToMany",
      "target": "plugin::webtools.url-alias",
      "writable": true,
      "configurable": false,
      "editable": false,
      "visible": true,
      "unique": true
    },
    "Hero": {
      "type": "component",
      "repeatable": false,
      "component": "shared.hero-section"
    },
    "Products": {
      "type": "component",
      "repeatable": true,
      "component": "shared.text-image-section"
    },
    "firstHeadingAfterHero": {
      "type": "string"
    },
    "Features": {
      "type": "component",
      "repeatable": true,
      "component": "shared.info-section"
    },
    "finalCTA": {
      "type": "component",
      "repeatable": true,
      "component": "shared.cta"
    },
    "Menu": {
      "type": "component",
      "repeatable": true,
      "component": "shared.menu"
    },
    "SEO": {
      "type": "component",
      "repeatable": false,
      "component": "shared.seo"
    },
    "testimonials": {
      "type": "component",
      "repeatable": false,
      "component": "shared.testimonials"
    },
    "FAQ": {
      "type": "component",
      "repeatable": false,
      "component": "shared.faq"
    }
  }
}
